streamlit_agraph/ConfigBuilder.py
streamlit_agraph/__init__.py
streamlit_agraph/algos.py
streamlit_agraph/config.py
streamlit_agraph/data.py
streamlit_agraph/edge.py
streamlit_agraph/node.py
streamlit_agraph/triple.py
streamlit_agraph/triplestore.py
streamlit_agraph/frontend/build/asset-manifest.json
streamlit_agraph/frontend/build/bootstrap.min.css
streamlit_agraph/frontend/build/index.html
streamlit_agraph/frontend/build/precache-manifest.71fb7882fe91d6cecff6d034905a184b.js
streamlit_agraph/frontend/build/service-worker.js
streamlit_agraph/frontend/build/static/css/2.67975c90.chunk.css
streamlit_agraph/frontend/build/static/css/2.67975c90.chunk.css.map
streamlit_agraph/frontend/build/static/js/2.2b44160c.chunk.js
streamlit_agraph/frontend/build/static/js/2.2b44160c.chunk.js.LICENSE.txt
streamlit_agraph/frontend/build/static/js/2.2b44160c.chunk.js.map
streamlit_agraph/frontend/build/static/js/main.df689717.chunk.js
streamlit_agraph/frontend/build/static/js/main.df689717.chunk.js.map
streamlit_agraph/frontend/build/static/js/runtime-main.0f76dc34.js
streamlit_agraph/frontend/build/static/js/runtime-main.0f76dc34.js.map
streamlit_agraph-0.0.45.dist-info/LICENSE
streamlit_agraph-0.0.45.dist-info/METADATA
streamlit_agraph-0.0.45.dist-info/WHEEL
streamlit_agraph-0.0.45.dist-info/top_level.txt
streamlit_agraph-0.0.45.dist-info/RECORD
