Metadata-Version: 2.1
Name: streamlit-agraph
Version: 0.0.45
Summary: Interactive Graph Vis for Streamlit.
Home-page: https://github.com/ChrisChross/streamlit-agraph
Author: Christian Klose
Author-email: chris.klose@gmx.net
License: UNKNOWN
Platform: UNKNOWN
Requires-Python: >=3.6
License-File: LICENSE
